{
  "run_id": "mteb_hotpotqa_20260401_122512",
  "dataset_name": "hotpotqa",
  "embedding_model": "llama-embed-nemotron-8b",
  "retrieval_strategy": "LIGHT_RAG",
  "config_snapshot": {
    "retrieval_strategy": "LIGHT_RAG",
    "retrieval_k": 20,
    "pre_fusion_k": 150,
    "rrf_bm25_weight": 0.3,
    "rrf_vector_weight": 0.7,
    "rrf_k": 60,
    "corpus_shuffle_seed": 42,
    "max_queries": 0,
    "max_corpus": 0,
    "generation_enabled": true,
    "max_context_chars": 192512,
    "reranker_enabled": true,
    "reranker_top_n": 5,
    "rerank_failures": 0,
    "strategy_mismatches": 0,
    "corpus_total_available": 66576,
    "corpus_indexed": 500,
    "gen_zero_count": 5,
    "gen_nonzero_count": 24,
    "dev_mode": true,
    "strategy_actual": "LIGHT_RAG",
    "dev_queries": 29,
    "dev_corpus_size": 500,
    "kg_max_hops": 2,
    "kg_max_text_chars": 9000,
    "kg_max_entities": 0,
    "kg_graph_weight": 0.4,
    "kg_vector_weight": 0.6,
    "max_graph_expansion": 30,
    "kg_cache_dir": null
  },
  "num_queries_evaluated": 29,
  "num_queries_failed": 0,
  "total_documents": 500,
  "avg_hit_rate_at_5": 0.7931,
  "avg_mrr": 0.5182,
  "avg_recall_at_k": {
    "1": 0.1379,
    "3": 0.4655,
    "5": 0.6897,
    "10": 0.931,
    "20": 0.9828
  },
  "avg_ndcg_at_k": {
    "1": 0.2759,
    "3": 0.4115,
    "5": 0.5243,
    "10": 0.6224,
    "20": 0.6379
  },
  "retrieval_complement_recall_at_k": {
    "1": 0.8621,
    "3": 0.5345,
    "5": 0.3103,
    "10": 0.069,
    "20": 0.0172
  },
  "avg_retrieved_count": 20.0,
  "avg_expected_count": 2.0,
  "avg_generation_recall": 0.9828,
  "avg_generation_hit": 1.0,
  "reranker_rescue_count": 0,
  "avg_generation_score": 0.7755,
  "execution_time_seconds": 901.23,
  "timestamp": "2026-04-01T12:40:13.629182",
  "status": "completed",
  "query_results": [
    {
      "query_id": "q_1547",
      "query_text": "What was Iqbal F. Qadir on when he participated in an attack on a radar station located on western shore of the Okhamandal Peninsula?",
      "dataset_name": "hotpotqa",
      "dataset_type": "HYBRID",
      "retrieved_doc_ids": [
        "doc_b4f7c87b8184",
        "doc_b42a6b21f246",
        "doc_fadfd6a4ebf6",
        "doc_4faa4bf92caa",
        "doc_605f61d1da7d",
        "doc_139b160626df",
        "doc_4c3a0c2fd6fb",
        "doc_f1f7fc470259",
        "doc_fa00bc3c974f",
        "doc_02c906dcfea6",
        "doc_9ef67372a3dd",
        "doc_5fdf6c4bf8d4",
        "doc_cb551c86450e",
        "doc_5169828aec2d",
        "doc_8bb064ebb3b5",
        "doc_55e3040f0f86",
        "doc_31d6ca949522",
        "doc_e3bf4b9ec735",
        "doc_a0b16e22e91d",
        "doc_2ae3cb371d31"
      ],
      "hit_at_k": {
        "1": 0.0,
        "3": 1.0,
        "5": 1.0,
        "10": 1.0,
        "20": 1.0
      },
      "recall_at_k": {
        "1": 0.0,
        "3": 0.5,
        "5": 1.0,
        "10": 1.0,
        "20": 1.0
      },
      "ndcg_at_k": {
        "1": 0.0,
        "3": 0.38685280723454163,
        "5": 0.6509209298071326,
        "10": 0.6509209298071326,
        "20": 0.6509209298071326
      },
      "mrr": 0.5,
      "generated_response": "flotilla",
      "expected_response": "flotilla",
      "primary_metric_type": "f1_score",
      "primary_metric_value": 1.0,
      "secondary_metrics": {
        "exact_match": 1.0,
        "faithfulness": 1.0
      },
      "status": "completed",
      "generation_doc_ids": [
        "doc_4faa4bf92caa",
        "doc_b42a6b21f246",
        "doc_a0b16e22e91d",
        "doc_31d6ca949522",
        "doc_9ef67372a3dd"
      ],
      "generation_recall": 1.0,
      "generation_hit": 1.0,
      "pre_rerank_candidate_ids": [
        "doc_b4f7c87b8184",
        "doc_b42a6b21f246",
        "doc_fadfd6a4ebf6",
        "doc_4faa4bf92caa",
        "doc_605f61d1da7d",
        "doc_139b160626df",
        "doc_4c3a0c2fd6fb",
        "doc_f1f7fc470259",
        "doc_fa00bc3c974f",
        "doc_02c906dcfea6",
        "doc_9ef67372a3dd",
        "doc_5fdf6c4bf8d4",
        "doc_cb551c86450e",
        "doc_5169828aec2d",
        "doc_8bb064ebb3b5",
        "doc_55e3040f0f86",
        "doc_31d6ca949522",
        "doc_e3bf4b9ec735",
        "doc_a0b16e22e91d",
        "doc_2ae3cb371d31"
      ],
      "metadata": {
        "question_type": "bridge",
        "level": "hard",
        "reranked": true
      }
    },
    {
      "query_id": "q_2054",
      "query_text": "When did the park at which Tivolis Koncertsal is located open?",
      "dataset_name": "hotpotqa",
      "dataset_type": "HYBRID",
      "retrieved_doc_ids": [
        "doc_cbe587b1bb03",
        "doc_db0117c08d23",
        "doc_582b88fe6aa9",
        "doc_e85708a20961",
        "doc_86533e2b3daf",
        "doc_817641c65068",
        "doc_736c447b38f9",
        "doc_d6e4d57c81d0",
        "doc_00a04413b36b",
        "doc_5fdf6c4bf8d4",
        "doc_7deb27efc3ce",
        "doc_d610eb67b01c",
        "doc_5c4e4acc8dff",
        "doc_071a063f5e55",
        "doc_b4f7c87b8184",
        "doc_28aaff25d9f0",
        "doc_129e702e719c",
        "doc_a7e13a39f5b3",
        "doc_7c5d91c79a7b",
        "doc_afb77097a95a"
      ],
      "hit_at_k": {
        "1": 0.0,
        "3": 1.0,
        "5": 1.0,
        "10": 1.0,
        "20": 1.0
      },
      "recall_at_k": {
        "1": 0.0,
        "3": 0.5,
        "5": 0.5,
        "10": 1.0,
        "20": 1.0
      },
      "ndcg_at_k": {
        "1": 0.0,
        "3": 0.3065735963827292,
        "5": 0.3065735963827292,
        "10": 0.5249810332008933,
        "20": 0.5249810332008933
      },
      "mrr": 0.3333333333333333,
      "generated_response": "15 August 1843",
      "expected_response": "15 August 1843",
      "primary_metric_type": "f1_score",
      "primary_metric_value": 1.0,
      "secondary_metrics": {
        "exact_match": 1.0,
        "faithfulness": 1.0
      },
      "status": "completed",
      "generation_doc_ids": [
        "doc_817641c65068",
        "doc_582b88fe6aa9",
        "doc_cbe587b1bb03",
        "doc_e85708a20961",
        "doc_28aaff25d9f0"
      ],
      "generation_recall": 1.0,
      "generation_hit": 1.0,
      "pre_rerank_candidate_ids": [
        "doc_cbe587b1bb03",
        "doc_db0117c08d23",
        "doc_582b88fe6aa9",
        "doc_e85708a20961",
        "doc_86533e2b3daf",
        "doc_817641c65068",
        "doc_736c447b38f9",
        "doc_d6e4d57c81d0",
        "doc_00a04413b36b",
        "doc_5fdf6c4bf8d4",
        "doc_7deb27efc3ce",
        "doc_d610eb67b01c",
        "doc_5c4e4acc8dff",
        "doc_071a063f5e55",
        "doc_b4f7c87b8184",
        "doc_28aaff25d9f0",
        "doc_129e702e719c",
        "doc_a7e13a39f5b3",
        "doc_7c5d91c79a7b",
        "doc_afb77097a95a"
      ],
      "metadata": {
        "question_type": "bridge",
        "level": "hard",
        "reranked": true
      }
    },
    {
      "query_id": "q_478",
      "query_text": "What is the shared country of ancestry between Art Laboe and Scout Tufankjian?",
      "dataset_name": "hotpotqa",
      "dataset_type": "HYBRID",
      "retrieved_doc_ids": [
        "doc_00a04413b36b",
        "doc_9564b5b3acad",
        "doc_caed5196ecaf",
        "doc_0995a2f3e44e",
        "doc_9ef67372a3dd",
        "doc_1a7bd60877a7",
        "doc_77d6eeaa11ac",
        "doc_55bdb7a9c8e9",
        "doc_087264da0848",
        "doc_7e4f47d4508c",
        "doc_129e702e719c",
        "doc_15ddd6283333",
        "doc_c3dff2c9c88d",
        "doc_b6eeb54f8777",
        "doc_82c5da55ef62",
        "doc_86e0883be37b",
        "doc_f5795fa1d361",
        "doc_a1825ef4f106",
        "doc_7c5d91c79a7b",
        "doc_a82ced61114c"
      ],
      "hit_at_k": {
        "1": 0.0,
        "3": 1.0,
        "5": 1.0,
        "10": 1.0,
        "20": 1.0
      },
      "recall_at_k": {
        "1": 0.0,
        "3": 1.0,
        "5": 1.0,
        "10": 1.0,
        "20": 1.0
      },
      "ndcg_at_k": {
        "1": 0.0,
        "3": 0.6934264036172708,
        "5": 0.6934264036172708,
        "10": 0.6934264036172708,
        "20": 0.6934264036172708
      },
      "mrr": 0.5,
      "generated_response": "Armenia",
      "expected_response": "Armenian",
      "primary_metric_type": "accuracy",
      "primary_metric_value": 0.0,
      "secondary_metrics": {
        "f1_score": 0.0,
        "exact_match": 0.0,
        "faithfulness": 0.2
      },
      "status": "completed",
      "generation_doc_ids": [
        "doc_9564b5b3acad",
        "doc_caed5196ecaf",
        "doc_86e0883be37b",
        "doc_129e702e719c",
        "doc_087264da0848"
      ],
      "generation_recall": 1.0,
      "generation_hit": 1.0,
      "pre_rerank_candidate_ids": [
        "doc_00a04413b36b",
        "doc_9564b5b3acad",
        "doc_caed5196ecaf",
        "doc_0995a2f3e44e",
        "doc_9ef67372a3dd",
        "doc_1a7bd60877a7",
        "doc_77d6eeaa11ac",
        "doc_55bdb7a9c8e9",
        "doc_087264da0848",
        "doc_7e4f47d4508c",
        "doc_129e702e719c",
        "doc_15ddd6283333",
        "doc_c3dff2c9c88d",
        "doc_b6eeb54f8777",
        "doc_82c5da55ef62",
        "doc_86e0883be37b",
        "doc_f5795fa1d361",
        "doc_a1825ef4f106",
        "doc_7c5d91c79a7b",
        "doc_a82ced61114c"
      ],
      "metadata": {
        "question_type": "comparison",
        "level": "hard",
        "reranked": true
      }
    },
    {
      "query_id": "q_3245",
      "query_text": "The school in which the Wilmslow Show is held is designated as what?",
      "dataset_name": "hotpotqa",
      "dataset_type": "HYBRID",
      "retrieved_doc_ids": [
        "doc_bc6fbe4f9468",
        "doc_e6db9982d142",
        "doc_4c59a12e1e85",
        "doc_67b9a1e6b986",
        "doc_65d035cca47c",
        "doc_00a04413b36b",
        "doc_bbf8d53bd208",
        "doc_8410daab81e7",
        "doc_a7e13a39f5b3",
        "doc_64e6fbb28feb",
        "doc_5ae543e8c139",
        "doc_acd962c04258",
        "doc_969a6f08f499",
        "doc_baae7588c8fb",
        "doc_04e483dd2f5c",
        "doc_3c00efdbc637",
        "doc_7e4f47d4508c",
        "doc_aa602713d5b8",
        "doc_dd525669996c",
        "doc_d6e4d57c81d0"
      ],
      "hit_at_k": {
        "1": 1.0,
        "3": 1.0,
        "5": 1.0,
        "10": 1.0,
        "20": 1.0
      },
      "recall_at_k": {
        "1": 0.5,
        "3": 0.5,
        "5": 1.0,
        "10": 1.0,
        "20": 1.0
      },
      "ndcg_at_k": {
        "1": 1.0,
        "3": 0.6131471927654584,
        "5": 0.8772153153380493,
        "10": 0.8772153153380493,
        "20": 0.8772153153380493
      },
      "mrr": 1.0,
      "generated_response": "good",
      "expected_response": "Centre of Excellence",
      "primary_metric_type": "f1_score",
      "primary_metric_value": 0.0,
      "secondary_metrics": {
        "exact_match": 0.0,
        "faithfulness": 1.0
      },
      "status": "completed",
      "generation_doc_ids": [
        "doc_bc6fbe4f9468",
        "doc_67b9a1e6b986",
        "doc_e6db9982d142",
        "doc_dd525669996c",
        "doc_4c59a12e1e85"
      ],
      "generation_recall": 1.0,
      "generation_hit": 1.0,
      "pre_rerank_candidate_ids": [
        "doc_bc6fbe4f9468",
        "doc_e6db9982d142",
        "doc_4c59a12e1e85",
        "doc_67b9a1e6b986",
        "doc_65d035cca47c",
        "doc_00a04413b36b",
        "doc_bbf8d53bd208",
        "doc_8410daab81e7",
        "doc_a7e13a39f5b3",
        "doc_64e6fbb28feb",
        "doc_5ae543e8c139",
        "doc_acd962c04258",
        "doc_969a6f08f499",
        "doc_baae7588c8fb",
        "doc_04e483dd2f5c",
        "doc_3c00efdbc637",
        "doc_7e4f47d4508c",
        "doc_aa602713d5b8",
        "doc_dd525669996c",
        "doc_d6e4d57c81d0"
      ],
      "metadata": {
        "question_type": "bridge",
        "level": "hard",
        "reranked": true
      }
    },
    {
      "query_id": "q_1119",
      "query_text": "Who will Billy Howle be seen opposite in the upcoming British drama film directed by Dominic Cooke?",
      "dataset_name": "hotpotqa",
      "dataset_type": "HYBRID",
      "retrieved_doc_ids": [
        "doc_b74067dfbccf",
        "doc_2e748b88eee6",
        "doc_0a9edcc306f5",
        "doc_bc7c6089d5ef",
        "doc_c79df9a1cdc9",
        "doc_4cb1bf79a1cd",
        "doc_14519ccf77ed",
        "doc_d6e4d57c81d0",
        "doc_8d00e9f90e5f",
        "doc_218d30d50b75",
        "doc_af5deab52e58",
        "doc_baae7588c8fb",
        "doc_9156ca9d0589",
        "doc_8b758fdc9ceb",
        "doc_fbea6547c451",
        "doc_8b75cb852844",
        "doc_78f729ac62f6",
        "doc_9ca9a6128e46",
        "doc_a5544235543c",
        "doc_51294a8ce854"
      ],
      "hit_at_k": {
        "1": 0.0,
        "3": 0.0,
        "5": 0.0,
        "10": 1.0,
        "20": 1.0
      },
      "recall_at_k": {
        "1": 0.0,
        "3": 0.0,
        "5": 0.0,
        "10": 1.0,
        "20": 1.0
      },
      "ndcg_at_k": {
        "1": 0.0,
        "3": 0.0,
        "5": 0.0,
        "10": 0.4227898344066503,
        "20": 0.4227898344066503
      },
      "mrr": 0.16666666666666666,
      "generated_response": "Saoirse Ronan",
      "expected_response": "Saoirse Ronan",
      "primary_metric_type": "f1_score",
      "primary_metric_value": 1.0,
      "secondary_metrics": {
        "exact_match": 1.0,
        "faithfulness": 1.0
      },
      "status": "completed",
      "generation_doc_ids": [
        "doc_4cb1bf79a1cd",
        "doc_14519ccf77ed",
        "doc_51294a8ce854",
        "doc_c79df9a1cdc9",
        "doc_a5544235543c"
      ],
      "generation_recall": 1.0,
      "generation_hit": 1.0,
      "pre_rerank_candidate_ids": [
        "doc_b74067dfbccf",
        "doc_2e748b88eee6",
        "doc_0a9edcc306f5",
        "doc_bc7c6089d5ef",
        "doc_c79df9a1cdc9",
        "doc_4cb1bf79a1cd",
        "doc_14519ccf77ed",
        "doc_d6e4d57c81d0",
        "doc_8d00e9f90e5f",
        "doc_218d30d50b75",
        "doc_af5deab52e58",
        "doc_baae7588c8fb",
        "doc_9156ca9d0589",
        "doc_8b758fdc9ceb",
        "doc_fbea6547c451",
        "doc_8b75cb852844",
        "doc_78f729ac62f6",
        "doc_9ca9a6128e46",
        "doc_a5544235543c",
        "doc_51294a8ce854"
      ],
      "metadata": {
        "question_type": "bridge",
        "level": "hard",
        "reranked": true
      }
    },
    {
      "query_id": "q_3575",
      "query_text": "What animated movie, starring Danny Devito, featured music written and produced by Kool Kojak?",
      "dataset_name": "hotpotqa",
      "dataset_type": "HYBRID",
      "retrieved_doc_ids": [
        "doc_e1f1d6e98de7",
        "doc_5c772e0cc9ef",
        "doc_5986bde91db9",
        "doc_6a161bb8067e",
        "doc_4f4cecf5886a",
        "doc_a82ced61114c",
        "doc_f167f6a7caab",
        "doc_a5544235543c",
        "doc_0b371a557cb7",
        "doc_3a8db9ed74f4",
        "doc_071a063f5e55",
        "doc_d09cd957ea11",
        "doc_6af21c618760",
        "doc_acad2514fd57",
        "doc_65d035cca47c",
        "doc_af5deab52e58",
        "doc_67ee46d848f9",
        "doc_afb77097a95a",
        "doc_a71ce3b1794b",
        "doc_77d6eeaa11ac"
      ],
      "hit_at_k": {
        "1": 0.0,
        "3": 1.0,
        "5": 1.0,
        "10": 1.0,
        "20": 1.0
      },
      "recall_at_k": {
        "1": 0.0,
        "3": 0.5,
        "5": 1.0,
        "10": 1.0,
        "20": 1.0
      },
      "ndcg_at_k": {
        "1": 0.0,
        "3": 0.38685280723454163,
        "5": 0.6240505200038379,
        "10": 0.6240505200038379,
        "20": 0.6240505200038379
      },
      "mrr": 0.5,
      "generated_response": "The Lorax",
      "expected_response": "The Lorax",
      "primary_metric_type": "f1_score",
      "primary_metric_value": 1.0,
      "secondary_metrics": {
        "exact_match": 1.0,
        "faithfulness": 1.0
      },
      "status": "completed",
      "generation_doc_ids": [
        "doc_5c772e0cc9ef",
        "doc_4f4cecf5886a",
        "doc_5986bde91db9",
        "doc_e1f1d6e98de7",
        "doc_6af21c618760"
      ],
      "generation_recall": 1.0,
      "generation_hit": 1.0,
      "pre_rerank_candidate_ids": [
        "doc_e1f1d6e98de7",
        "doc_5c772e0cc9ef",
        "doc_5986bde91db9",
        "doc_6a161bb8067e",
        "doc_4f4cecf5886a",
        "doc_a82ced61114c",
        "doc_f167f6a7caab",
        "doc_a5544235543c",
        "doc_0b371a557cb7",
        "doc_3a8db9ed74f4",
        "doc_071a063f5e55",
        "doc_d09cd957ea11",
        "doc_6af21c618760",
        "doc_acad2514fd57",
        "doc_65d035cca47c",
        "doc_af5deab52e58",
        "doc_67ee46d848f9",
        "doc_afb77097a95a",
        "doc_a71ce3b1794b",
        "doc_77d6eeaa11ac"
      ],
      "metadata": {
        "question_type": "bridge",
        "level": "hard",
        "reranked": true
      }
    },
    {
      "query_id": "q_978",
      "query_text": "Out of the actors who have played the role of Luc Deveraux in the Universal Soldier franchise, which actor has also starred in the movies Holby City, Doctor Strange, the Bourne Ultimatum and Zero Dark Thirty?",
      "dataset_name": "hotpotqa",
      "dataset_type": "HYBRID",
      "retrieved_doc_ids": [
        "doc_5e3ddd9b8e42",
        "doc_ed5518e5247e",
        "doc_d929f815af19",
        "doc_9c37c1b457ca",
        "doc_af5deab52e58",
        "doc_4cb1bf79a1cd",
        "doc_2e748b88eee6",
        "doc_a5544235543c",
        "doc_0a69dab11fa9",
        "doc_2c22a8ee8a80",
        "doc_a1825ef4f106",
        "doc_9ff4412cb0d8",
        "doc_a55ca63bc0ad",
        "doc_8c1e6c4750b1",
        "doc_78f729ac62f6",
        "doc_54240e957eb0",
        "doc_51294a8ce854",
        "doc_6896cccddfb3",
        "doc_e1927a863a17",
        "doc_7b55c6991c02"
      ],
      "hit_at_k": {
        "1": 0.0,
        "3": 1.0,
        "5": 1.0,
        "10": 1.0,
        "20": 1.0
      },
      "recall_at_k": {
        "1": 0.0,
        "3": 0.5,
        "5": 1.0,
        "10": 1.0,
        "20": 1.0
      },
      "ndcg_at_k": {
        "1": 0.0,
        "3": 0.3065735963827292,
        "5": 0.5706417189553201,
        "10": 0.5706417189553201,
        "20": 0.5706417189553201
      },
      "mrr": 0.3333333333333333,
      "generated_response": "Scott Adkins",
      "expected_response": "Scott Adkins",
      "primary_metric_type": "f1_score",
      "primary_metric_value": 1.0,
      "secondary_metrics": {
        "exact_match": 1.0,
        "faithfulness": 1.0
      },
      "status": "completed",
      "generation_doc_ids": [
        "doc_d929f815af19",
        "doc_9c37c1b457ca",
        "doc_6896cccddfb3",
        "doc_7b55c6991c02",
        "doc_51294a8ce854"
      ],
      "generation_recall": 1.0,
      "generation_hit": 1.0,
      "pre_rerank_candidate_ids": [
        "doc_5e3ddd9b8e42",
        "doc_ed5518e5247e",
        "doc_d929f815af19",
        "doc_9c37c1b457ca",
        "doc_af5deab52e58",
        "doc_4cb1bf79a1cd",
        "doc_2e748b88eee6",
        "doc_a5544235543c",
        "doc_0a69dab11fa9",
        "doc_2c22a8ee8a80",
        "doc_a1825ef4f106",
        "doc_9ff4412cb0d8",
        "doc_a55ca63bc0ad",
        "doc_8c1e6c4750b1",
        "doc_78f729ac62f6",
        "doc_54240e957eb0",
        "doc_51294a8ce854",
        "doc_6896cccddfb3",
        "doc_e1927a863a17",
        "doc_7b55c6991c02"
      ],
      "metadata": {
        "question_type": "bridge",
        "level": "hard",
        "reranked": true
      }
    },
    {
      "query_id": "q_1668",
      "query_text": "Tommy's Honour was a drama film that included the actor who found success with what 2016 BBC miniseries?",
      "dataset_name": "hotpotqa",
      "dataset_type": "HYBRID",
      "retrieved_doc_ids": [
        "doc_6f0f1f67cd06",
        "doc_b74067dfbccf",
        "doc_ecd34fb3f5b2",
        "doc_cb551c86450e",
        "doc_4cb1bf79a1cd",
        "doc_2e748b88eee6",
        "doc_c79df9a1cdc9",
        "doc_14519ccf77ed",
        "doc_51294a8ce854",
        "doc_daf00a922da9",
        "doc_7b55c6991c02",
        "doc_8552114e16bc",
        "doc_0d48addd4a1e",
        "doc_754e7c21452d",
        "doc_218d30d50b75",
        "doc_9ca9a6128e46",
        "doc_9c37c1b457ca",
        "doc_a5544235543c",
        "doc_78f729ac62f6",
        "doc_9156ca9d0589"
      ],
      "hit_at_k": {
        "1": 0.0,
        "3": 0.0,
        "5": 0.0,
        "10": 1.0,
        "20": 1.0
      },
      "recall_at_k": {
        "1": 0.0,
        "3": 0.0,
        "5": 0.0,
        "10": 1.0,
        "20": 1.0
      },
      "ndcg_at_k": {
        "1": 0.0,
        "3": 0.0,
        "5": 0.0,
        "10": 0.3889580943680543,
        "20": 0.3889580943680543
      },
      "mrr": 0.14285714285714285,
      "generated_response": "War & Peace",
      "expected_response": "War & Peace",
      "primary_metric_type": "f1_score",
      "primary_metric_value": 1.0,
      "secondary_metrics": {
        "exact_match": 1.0,
        "faithfulness": 1.0
      },
      "status": "completed",
      "generation_doc_ids": [
        "doc_c79df9a1cdc9",
        "doc_51294a8ce854",
        "doc_4cb1bf79a1cd",
        "doc_9c37c1b457ca",
        "doc_2e748b88eee6"
      ],
      "generation_recall": 1.0,
      "generation_hit": 1.0,
      "pre_rerank_candidate_ids": [
        "doc_6f0f1f67cd06",
        "doc_b74067dfbccf",
        "doc_ecd34fb3f5b2",
        "doc_cb551c86450e",
        "doc_4cb1bf79a1cd",
        "doc_2e748b88eee6",
        "doc_c79df9a1cdc9",
        "doc_14519ccf77ed",
        "doc_51294a8ce854",
        "doc_daf00a922da9",
        "doc_7b55c6991c02",
        "doc_8552114e16bc",
        "doc_0d48addd4a1e",
        "doc_754e7c21452d",
        "doc_218d30d50b75",
        "doc_9ca9a6128e46",
        "doc_9c37c1b457ca",
        "doc_a5544235543c",
        "doc_78f729ac62f6",
        "doc_9156ca9d0589"
      ],
      "metadata": {
        "question_type": "bridge",
        "level": "hard",
        "reranked": true
      }
    },
    {
      "query_id": "q_6149",
      "query_text": "Which rock band chose its name by drawing it out of a hat, Switchfoot or Midnight Oil?",
      "dataset_name": "hotpotqa",
      "dataset_type": "HYBRID",
      "retrieved_doc_ids": [
        "doc_ed1dd6197c06",
        "doc_eca6d249d242",
        "doc_8edb5cd610e9",
        "doc_44076348833d",
        "doc_5e233a782b86",
        "doc_bbc866fee46a",
        "doc_00a04413b36b",
        "doc_309f0fba54dd",
        "doc_129e702e719c",
        "doc_578c760cb8d3",
        "doc_0995a2f3e44e",
        "doc_afb77097a95a",
        "doc_3c00efdbc637",
        "doc_e361928bea97",
        "doc_5e0b688d7364",
        "doc_d6e4d57c81d0",
        "doc_05d515c8c0d4",
        "doc_fecd101da4b7",
        "doc_a82ced61114c",
        "doc_1142c8d7d2e5"
      ],
      "hit_at_k": {
        "1": 0.0,
        "3": 0.0,
        "5": 0.0,
        "10": 1.0,
        "20": 1.0
      },
      "recall_at_k": {
        "1": 0.0,
        "3": 0.0,
        "5": 0.0,
        "10": 1.0,
        "20": 1.0
      },
      "ndcg_at_k": {
        "1": 0.0,
        "3": 0.0,
        "5": 0.0,
        "10": 0.39564672360221187,
        "20": 0.39564672360221187
      },
      "mrr": 0.16666666666666666,
      "generated_response": "Midnight Oil",
      "expected_response": "Midnight Oil",
      "primary_metric_type": "accuracy",
      "primary_metric_value": 1.0,
      "secondary_metrics": {
        "f1_score": 1.0,
        "exact_match": 1.0,
        "faithfulness": 1.0
      },
      "status": "completed",
      "generation_doc_ids": [
        "doc_578c760cb8d3",
        "doc_bbc866fee46a",
        "doc_00a04413b36b",
        "doc_309f0fba54dd",
        "doc_44076348833d"
      ],
      "generation_recall": 1.0,
      "generation_hit": 1.0,
      "pre_rerank_candidate_ids": [
        "doc_ed1dd6197c06",
        "doc_eca6d249d242",
        "doc_8edb5cd610e9",
        "doc_44076348833d",
        "doc_5e233a782b86",
        "doc_bbc866fee46a",
        "doc_00a04413b36b",
        "doc_309f0fba54dd",
        "doc_129e702e719c",
        "doc_578c760cb8d3",
        "doc_0995a2f3e44e",
        "doc_afb77097a95a",
        "doc_3c00efdbc637",
        "doc_e361928bea97",
        "doc_5e0b688d7364",
        "doc_d6e4d57c81d0",
        "doc_05d515c8c0d4",
        "doc_fecd101da4b7",
        "doc_a82ced61114c",
        "doc_1142c8d7d2e5"
      ],
      "metadata": {
        "question_type": "comparison",
        "level": "hard",
        "reranked": true
      }
    },
    {
      "query_id": "q_4237",
      "query_text": "\"Tunak\", is a bhangra/pop love song by an artist born in which year ?",
      "dataset_name": "hotpotqa",
      "dataset_type": "HYBRID",
      "retrieved_doc_ids": [
        "doc_7c5d91c79a7b",
        "doc_1dfc3de9af07",
        "doc_a71ce3b1794b",
        "doc_4e76ad8d3b34",
        "doc_9564b5b3acad",
        "doc_5c772e0cc9ef",
        "doc_a1825ef4f106",
        "doc_6b7faf7c8843",
        "doc_fae5f199e80d",
        "doc_6a86ec45ff1c",
        "doc_81b73d30bbb9",
        "doc_15ddd6283333",
        "doc_29ec945f558a",
        "doc_0be3e31db230",
        "doc_8bff5d43c2cd",
        "doc_baae7588c8fb",
        "doc_8d00e9f90e5f",
        "doc_d966845ed38a",
        "doc_6a161bb8067e",
        "doc_77d6eeaa11ac"
      ],
      "hit_at_k": {
        "1": 0.0,
        "3": 0.0,
        "5": 1.0,
        "10": 1.0,
        "20": 1.0
      },
      "recall_at_k": {
        "1": 0.0,
        "3": 0.0,
        "5": 0.5,
        "10": 1.0,
        "20": 1.0
      },
      "ndcg_at_k": {
        "1": 0.0,
        "3": 0.0,
        "5": 0.2640681225725909,
        "10": 0.45749452618986164,
        "20": 0.45749452618986164
      },
      "mrr": 0.25,
      "generated_response": "1967",
      "expected_response": "1967",
      "primary_metric_type": "f1_score",
      "primary_metric_value": 1.0,
      "secondary_metrics": {
        "exact_match": 1.0,
        "faithfulness": 1.0
      },
      "status": "completed",
      "generation_doc_ids": [
        "doc_4e76ad8d3b34",
        "doc_6b7faf7c8843",
        "doc_81b73d30bbb9",
        "doc_d966845ed38a",
        "doc_15ddd6283333"
      ],
      "generation_recall": 1.0,
      "generation_hit": 1.0,
      "pre_rerank_candidate_ids": [
        "doc_7c5d91c79a7b",
        "doc_1dfc3de9af07",
        "doc_a71ce3b1794b",
        "doc_4e76ad8d3b34",
        "doc_9564b5b3acad",
        "doc_5c772e0cc9ef",
        "doc_a1825ef4f106",
        "doc_6b7faf7c8843",
        "doc_fae5f199e80d",
        "doc_6a86ec45ff1c",
        "doc_81b73d30bbb9",
        "doc_15ddd6283333",
        "doc_29ec945f558a",
        "doc_0be3e31db230",
        "doc_8bff5d43c2cd",
        "doc_baae7588c8fb",
        "doc_8d00e9f90e5f",
        "doc_d966845ed38a",
        "doc_6a161bb8067e",
        "doc_77d6eeaa11ac"
      ],
      "metadata": {
        "question_type": "bridge",
        "level": "hard",
        "reranked": true
      }
    },
    {
      "query_id": "q_1106",
      "query_text": "Which Captain launched the attack which led to more casualties than any other incident in the war fought between the settlers of the nascent colony of New Netherland and the native Lenape population?",
      "dataset_name": "hotpotqa",
      "dataset_type": "HYBRID",
      "retrieved_doc_ids": [
        "doc_76d5c77c3855",
        "doc_86e0883be37b",
        "doc_12d8cdba9155",
        "doc_031d2763fccc",
        "doc_55e3040f0f86",
        "doc_ac3554456786",
        "doc_b4f7c87b8184",
        "doc_4faa4bf92caa",
        "doc_e23beb1b5290",
        "doc_b72d2f144ef8",
        "doc_5e0b688d7364",
        "doc_6f1b04a03da2",
        "doc_5b8c7d3e87ca",
        "doc_77d6eeaa11ac",
        "doc_129e702e719c",
        "doc_3952dbef23ec",
        "doc_5fa39b772df5",
        "doc_4c3a0c2fd6fb",
        "doc_b6654cded89f",
        "doc_071a063f5e55"
      ],
      "hit_at_k": {
        "1": 0.0,
        "3": 0.0,
        "5": 0.0,
        "10": 1.0,
        "20": 1.0
      },
      "recall_at_k": {
        "1": 0.0,
        "3": 0.0,
        "5": 0.0,
        "10": 1.0,
        "20": 1.0
      },
      "ndcg_at_k": {
        "1": 0.0,
        "3": 0.0,
        "5": 0.0,
        "10": 0.40298313359773236,
        "20": 0.40298313359773236
      },
      "mrr": 0.16666666666666666,
      "generated_response": "John Underhill",
      "expected_response": "Captain John Underhill",
      "primary_metric_type": "f1_score",
      "primary_metric_value": 0.8,
      "secondary_metrics": {
        "exact_match": 0.0,
        "faithfulness": 1.0
      },
      "status": "completed",
      "generation_doc_ids": [
        "doc_e23beb1b5290",
        "doc_ac3554456786",
        "doc_5fa39b772df5",
        "doc_12d8cdba9155",
        "doc_4c3a0c2fd6fb"
      ],
      "generation_recall": 1.0,
      "generation_hit": 1.0,
      "pre_rerank_candidate_ids": [
        "doc_76d5c77c3855",
        "doc_86e0883be37b",
        "doc_12d8cdba9155",
        "doc_031d2763fccc",
        "doc_55e3040f0f86",
        "doc_ac3554456786",
        "doc_b4f7c87b8184",
        "doc_4faa4bf92caa",
        "doc_e23beb1b5290",
        "doc_b72d2f144ef8",
        "doc_5e0b688d7364",
        "doc_6f1b04a03da2",
        "doc_5b8c7d3e87ca",
        "doc_77d6eeaa11ac",
        "doc_129e702e719c",
        "doc_3952dbef23ec",
        "doc_5fa39b772df5",
        "doc_4c3a0c2fd6fb",
        "doc_b6654cded89f",
        "doc_071a063f5e55"
      ],
      "metadata": {
        "question_type": "bridge",
        "level": "hard",
        "reranked": true
      }
    },
    {
      "query_id": "q_6953",
      "query_text": "In which film did Emilio Estevez star in in the same year as Nightmares",
      "dataset_name": "hotpotqa",
      "dataset_type": "HYBRID",
      "retrieved_doc_ids": [
        "doc_decab0c612f1",
        "doc_5e3ddd9b8e42",
        "doc_62e150e0ea3f",
        "doc_cb551c86450e",
        "doc_4d9704d6db79",
        "doc_7c5d91c79a7b",
        "doc_8d00e9f90e5f",
        "doc_b4f7c87b8184",
        "doc_f70086c00f28",
        "doc_7e47fd633107",
        "doc_f5795fa1d361",
        "doc_bbf8d53bd208",
        "doc_65d035cca47c",
        "doc_afb77097a95a",
        "doc_d6e4d57c81d0",
        "doc_c5536276d3f3",
        "doc_8b75cb852844",
        "doc_67ee46d848f9",
        "doc_af5deab52e58",
        "doc_5ae543e8c139"
      ],
      "hit_at_k": {
        "1": 0.0,
        "3": 1.0,
        "5": 1.0,
        "10": 1.0,
        "20": 1.0
      },
      "recall_at_k": {
        "1": 0.0,
        "3": 0.5,
        "5": 1.0,
        "10": 1.0,
        "20": 1.0
      },
      "ndcg_at_k": {
        "1": 0.0,
        "3": 0.38685280723454163,
        "5": 0.6240505200038379,
        "10": 0.6240505200038379,
        "20": 0.6240505200038379
      },
      "mrr": 0.5,
      "generated_response": "The Outsiders",
      "expected_response": "The Outsiders",
      "primary_metric_type": "f1_score",
      "primary_metric_value": 1.0,
      "secondary_metrics": {
        "exact_match": 1.0,
        "faithfulness": 1.0
      },
      "status": "completed",
      "generation_doc_ids": [
        "doc_4d9704d6db79",
        "doc_5e3ddd9b8e42",
        "doc_62e150e0ea3f",
        "doc_65d035cca47c",
        "doc_decab0c612f1"
      ],
      "generation_recall": 1.0,
      "generation_hit": 1.0,
      "pre_rerank_candidate_ids": [
        "doc_decab0c612f1",
        "doc_5e3ddd9b8e42",
        "doc_62e150e0ea3f",
        "doc_cb551c86450e",
        "doc_4d9704d6db79",
        "doc_7c5d91c79a7b",
        "doc_8d00e9f90e5f",
        "doc_b4f7c87b8184",
        "doc_f70086c00f28",
        "doc_7e47fd633107",
        "doc_f5795fa1d361",
        "doc_bbf8d53bd208",
        "doc_65d035cca47c",
        "doc_afb77097a95a",
        "doc_d6e4d57c81d0",
        "doc_c5536276d3f3",
        "doc_8b75cb852844",
        "doc_67ee46d848f9",
        "doc_af5deab52e58",
        "doc_5ae543e8c139"
      ],
      "metadata": {
        "question_type": "bridge",
        "level": "hard",
        "reranked": true
      }
    },
    {
      "query_id": "q_2375",
      "query_text": "What was the concept of the business Eric S .Pistorius worked for after being an attorney?",
      "dataset_name": "hotpotqa",
      "dataset_type": "HYBRID",
      "retrieved_doc_ids": [
        "doc_ef7e887cd08e",
        "doc_a55ca63bc0ad",
        "doc_031d2763fccc",
        "doc_baae7588c8fb",
        "doc_ee49745c596a",
        "doc_5e0b688d7364",
        "doc_aab3ea271f9c",
        "doc_68ee4cbd2c11",
        "doc_a7e13a39f5b3",
        "doc_4c3a0c2fd6fb",
        "doc_a82ced61114c",
        "doc_65d035cca47c",
        "doc_d9126f8eda68",
        "doc_3001b694602a",
        "doc_9ca9a6128e46",
        "doc_7c5d91c79a7b",
        "doc_8b75cb852844",
        "doc_f3b36a8f1edd",
        "doc_d6e4d57c81d0",
        "doc_9dc6f071bf77"
      ],
      "hit_at_k": {
        "1": 1.0,
        "3": 1.0,
        "5": 1.0,
        "10": 1.0,
        "20": 1.0
      },
      "recall_at_k": {
        "1": 0.5,
        "3": 0.5,
        "5": 0.5,
        "10": 0.5,
        "20": 0.5
      },
      "ndcg_at_k": {
        "1": 1.0,
        "3": 0.6131471927654584,
        "5": 0.6131471927654584,
        "10": 0.6131471927654584,
        "20": 0.6131471927654584
      },
      "mrr": 1.0,
      "generated_response": "law firm",
      "expected_response": "to ensure wide visibility and understanding of cases in a region",
      "primary_metric_type": "f1_score",
      "primary_metric_value": 0.0,
      "secondary_metrics": {
        "exact_match": 0.0,
        "faithfulness": 1.0
      },
      "status": "completed",
      "generation_doc_ids": [
        "doc_ef7e887cd08e",
        "doc_5e0b688d7364",
        "doc_68ee4cbd2c11",
        "doc_9dc6f071bf77",
        "doc_031d2763fccc"
      ],
      "generation_recall": 0.5,
      "generation_hit": 1.0,
      "pre_rerank_candidate_ids": [
        "doc_ef7e887cd08e",
        "doc_a55ca63bc0ad",
        "doc_031d2763fccc",
        "doc_baae7588c8fb",
        "doc_ee49745c596a",
        "doc_5e0b688d7364",
        "doc_aab3ea271f9c",
        "doc_68ee4cbd2c11",
        "doc_a7e13a39f5b3",
        "doc_4c3a0c2fd6fb",
        "doc_a82ced61114c",
        "doc_65d035cca47c",
        "doc_d9126f8eda68",
        "doc_3001b694602a",
        "doc_9ca9a6128e46",
        "doc_7c5d91c79a7b",
        "doc_8b75cb852844",
        "doc_f3b36a8f1edd",
        "doc_d6e4d57c81d0",
        "doc_9dc6f071bf77"
      ],
      "metadata": {
        "question_type": "bridge",
        "level": "hard",
        "reranked": true
      }
    },
    {
      "query_id": "q_5129",
      "query_text": "Which port city lies approximately 25 km north of the Lingnan Fine Arts Museum?",
      "dataset_name": "hotpotqa",
      "dataset_type": "HYBRID",
      "retrieved_doc_ids": [
        "doc_76ec15f72159",
        "doc_8dcbf6885877",
        "doc_7c5d91c79a7b",
        "doc_7deb27efc3ce",
        "doc_a82ced61114c",
        "doc_c37a79b46976",
        "doc_8410daab81e7",
        "doc_2d20ffc40fc7",
        "doc_f1f7fc470259",
        "doc_bf2f030998f8",
        "doc_d6e4d57c81d0",
        "doc_ef660eb73d13",
        "doc_2bbf0bf094d7",
        "doc_139b160626df",
        "doc_3c1214e16c85",
        "doc_3446c10d0490",
        "doc_f82f990f334a",
        "doc_fadfd6a4ebf6",
        "doc_f8c9396a7c29",
        "doc_eef7eb9558f2"
      ],
      "hit_at_k": {
        "1": 1.0,
        "3": 1.0,
        "5": 1.0,
        "10": 1.0,
        "20": 1.0
      },
      "recall_at_k": {
        "1": 0.5,
        "3": 1.0,
        "5": 1.0,
        "10": 1.0,
        "20": 1.0
      },
      "ndcg_at_k": {
        "1": 1.0,
        "3": 1.0,
        "5": 1.0,
        "10": 1.0,
        "20": 1.0
      },
      "mrr": 1.0,
      "generated_response": "Keelung",
      "expected_response": "Keelung",
      "primary_metric_type": "f1_score",
      "primary_metric_value": 1.0,
      "secondary_metrics": {
        "exact_match": 1.0,
        "faithfulness": 1.0
      },
      "status": "completed",
      "generation_doc_ids": [
        "doc_76ec15f72159",
        "doc_8dcbf6885877",
        "doc_bf2f030998f8",
        "doc_eef7eb9558f2",
        "doc_ef660eb73d13"
      ],
      "generation_recall": 1.0,
      "generation_hit": 1.0,
      "pre_rerank_candidate_ids": [
        "doc_76ec15f72159",
        "doc_8dcbf6885877",
        "doc_7c5d91c79a7b",
        "doc_7deb27efc3ce",
        "doc_a82ced61114c",
        "doc_c37a79b46976",
        "doc_8410daab81e7",
        "doc_2d20ffc40fc7",
        "doc_f1f7fc470259",
        "doc_bf2f030998f8",
        "doc_d6e4d57c81d0",
        "doc_ef660eb73d13",
        "doc_2bbf0bf094d7",
        "doc_139b160626df",
        "doc_3c1214e16c85",
        "doc_3446c10d0490",
        "doc_f82f990f334a",
        "doc_fadfd6a4ebf6",
        "doc_f8c9396a7c29",
        "doc_eef7eb9558f2"
      ],
      "metadata": {
        "question_type": "bridge",
        "level": "hard",
        "reranked": true
      }
    },
    {
      "query_id": "q_4491",
      "query_text": "Has Stefan Edberg won more events than  Édouard Roger-Vasselin?",
      "dataset_name": "hotpotqa",
      "dataset_type": "HYBRID",
      "retrieved_doc_ids": [
        "doc_4dd1d7bee06f",
        "doc_2c22a8ee8a80",
        "doc_9ca9a6128e46",
        "doc_a55ca63bc0ad",
        "doc_9b67791da6a1",
        "doc_64fa0bf26791",
        "doc_501ebdc6d35b",
        "doc_b98979630851",
        "doc_d7f22bd506e7",
        "doc_bbb90cde213b",
        "doc_79a38b4326ec",
        "doc_059c0c749c8f",
        "doc_baae7588c8fb",
        "doc_f5795fa1d361",
        "doc_f2bb89feac90",
        "doc_86e0883be37b",
        "doc_3001b694602a",
        "doc_d6e4d57c81d0",
        "doc_7c5d91c79a7b",
        "doc_8b75cb852844"
      ],
      "hit_at_k": {
        "1": 0.0,
        "3": 0.0,
        "5": 1.0,
        "10": 1.0,
        "20": 1.0
      },
      "recall_at_k": {
        "1": 0.0,
        "3": 0.0,
        "5": 0.5,
        "10": 1.0,
        "20": 1.0
      },
      "ndcg_at_k": {
        "1": 0.0,
        "3": 0.0,
        "5": 0.23719771276929622,
        "10": 0.4415801103577823,
        "20": 0.4415801103577823
      },
      "mrr": 0.2,
      "generated_response": "yes",
      "expected_response": "yes",
      "primary_metric_type": "accuracy",
      "primary_metric_value": 1.0,
      "secondary_metrics": {
        "f1_score": 1.0,
        "exact_match": 1.0,
        "faithfulness": 0.2
      },
      "status": "completed",
      "generation_doc_ids": [
        "doc_9b67791da6a1",
        "doc_501ebdc6d35b",
        "doc_8b75cb852844",
        "doc_9ca9a6128e46",
        "doc_4dd1d7bee06f"
      ],
      "generation_recall": 1.0,
      "generation_hit": 1.0,
      "pre_rerank_candidate_ids": [
        "doc_4dd1d7bee06f",
        "doc_2c22a8ee8a80",
        "doc_9ca9a6128e46",
        "doc_a55ca63bc0ad",
        "doc_9b67791da6a1",
        "doc_64fa0bf26791",
        "doc_501ebdc6d35b",
        "doc_b98979630851",
        "doc_d7f22bd506e7",
        "doc_bbb90cde213b",
        "doc_79a38b4326ec",
        "doc_059c0c749c8f",
        "doc_baae7588c8fb",
        "doc_f5795fa1d361",
        "doc_f2bb89feac90",
        "doc_86e0883be37b",
        "doc_3001b694602a",
        "doc_d6e4d57c81d0",
        "doc_7c5d91c79a7b",
        "doc_8b75cb852844"
      ],
      "metadata": {
        "question_type": "comparison",
        "level": "hard",
        "reranked": true
      }
    },
    {
      "query_id": "q_720",
      "query_text": " Jason Regler, stated that he had the idea for the flashing wristbands during a song built around which instrument ?",
      "dataset_name": "hotpotqa",
      "dataset_type": "HYBRID",
      "retrieved_doc_ids": [
        "doc_f8e369ad35cd",
        "doc_ed1dd6197c06",
        "doc_00a04413b36b",
        "doc_a82ced61114c",
        "doc_129e702e719c",
        "doc_44076348833d",
        "doc_eca6d249d242",
        "doc_e361928bea97",
        "doc_c7d9521ce0fa",
        "doc_3952dbef23ec",
        "doc_578c760cb8d3",
        "doc_169e39f705cc",
        "doc_0b371a557cb7",
        "doc_05d515c8c0d4",
        "doc_5e233a782b86",
        "doc_15ddd6283333",
        "doc_bbc866fee46a",
        "doc_d1c3e17bb733",
        "doc_5c4e4acc8dff",
        "doc_fecd101da4b7"
      ],
      "hit_at_k": {
        "1": 0.0,
        "3": 0.0,
        "5": 0.0,
        "10": 1.0,
        "20": 1.0
      },
      "recall_at_k": {
        "1": 0.0,
        "3": 0.0,
        "5": 0.0,
        "10": 0.5,
        "20": 1.0
      },
      "ndcg_at_k": {
        "1": 0.0,
        "3": 0.0,
        "5": 0.0,
        "10": 0.19342640361727081,
        "20": 0.3330217774820213
      },
      "mrr": 0.125,
      "generated_response": "organ",
      "expected_response": "an organ",
      "primary_metric_type": "f1_score",
      "primary_metric_value": 0.6667,
      "secondary_metrics": {
        "exact_match": 0.0,
        "faithfulness": 1.0
      },
      "status": "completed",
      "generation_doc_ids": [
        "doc_e361928bea97",
        "doc_fecd101da4b7",
        "doc_5e233a782b86",
        "doc_bbc866fee46a",
        "doc_a82ced61114c"
      ],
      "generation_recall": 1.0,
      "generation_hit": 1.0,
      "pre_rerank_candidate_ids": [
        "doc_f8e369ad35cd",
        "doc_ed1dd6197c06",
        "doc_00a04413b36b",
        "doc_a82ced61114c",
        "doc_129e702e719c",
        "doc_44076348833d",
        "doc_eca6d249d242",
        "doc_e361928bea97",
        "doc_c7d9521ce0fa",
        "doc_3952dbef23ec",
        "doc_578c760cb8d3",
        "doc_169e39f705cc",
        "doc_0b371a557cb7",
        "doc_05d515c8c0d4",
        "doc_5e233a782b86",
        "doc_15ddd6283333",
        "doc_bbc866fee46a",
        "doc_d1c3e17bb733",
        "doc_5c4e4acc8dff",
        "doc_fecd101da4b7"
      ],
      "metadata": {
        "question_type": "bridge",
        "level": "hard",
        "reranked": true
      }
    },
    {
      "query_id": "q_1205",
      "query_text": " The Soul of Buddha is a 1918 American silent romance film shot in a borough  that is the western terminus of what?",
      "dataset_name": "hotpotqa",
      "dataset_type": "HYBRID",
      "retrieved_doc_ids": [
        "doc_caed5196ecaf",
        "doc_e9fd65471f44",
        "doc_5fa39b772df5",
        "doc_869ec99e4399",
        "doc_e8bce744eea3",
        "doc_12d8cdba9155",
        "doc_8b2c101edba2",
        "doc_f1f7fc470259",
        "doc_ed5518e5247e",
        "doc_8457d4fb608e",
        "doc_acad2514fd57",
        "doc_a768e0317794",
        "doc_bb8f4d30e773",
        "doc_3671d1fad47c",
        "doc_1ed5e28f7b77",
        "doc_fcdf6bd6311d",
        "doc_dc9d2cbb06a4",
        "doc_0a9edcc306f5",
        "doc_27b6cda165ff",
        "doc_02c906dcfea6"
      ],
      "hit_at_k": {
        "1": 0.0,
        "3": 0.0,
        "5": 1.0,
        "10": 1.0,
        "20": 1.0
      },
      "recall_at_k": {
        "1": 0.0,
        "3": 0.0,
        "5": 0.5,
        "10": 1.0,
        "20": 1.0
      },
      "ndcg_at_k": {
        "1": 0.0,
        "3": 0.0,
        "5": 0.2640681225725909,
        "10": 0.48247555939075504,
        "20": 0.48247555939075504
      },
      "mrr": 0.25,
      "generated_response": "George Washington Bridge",
      "expected_response": "the George Washington Bridge",
      "primary_metric_type": "f1_score",
      "primary_metric_value": 0.8571,
      "secondary_metrics": {
        "exact_match": 0.0,
        "faithfulness": 1.0
      },
      "status": "completed",
      "generation_doc_ids": [
        "doc_869ec99e4399",
        "doc_12d8cdba9155",
        "doc_02c906dcfea6",
        "doc_3671d1fad47c",
        "doc_e9fd65471f44"
      ],
      "generation_recall": 1.0,
      "generation_hit": 1.0,
      "pre_rerank_candidate_ids": [
        "doc_caed5196ecaf",
        "doc_e9fd65471f44",
        "doc_5fa39b772df5",
        "doc_869ec99e4399",
        "doc_e8bce744eea3",
        "doc_12d8cdba9155",
        "doc_8b2c101edba2",
        "doc_f1f7fc470259",
        "doc_ed5518e5247e",
        "doc_8457d4fb608e",
        "doc_acad2514fd57",
        "doc_a768e0317794",
        "doc_bb8f4d30e773",
        "doc_3671d1fad47c",
        "doc_1ed5e28f7b77",
        "doc_fcdf6bd6311d",
        "doc_dc9d2cbb06a4",
        "doc_0a9edcc306f5",
        "doc_27b6cda165ff",
        "doc_02c906dcfea6"
      ],
      "metadata": {
        "question_type": "bridge",
        "level": "hard",
        "reranked": true
      }
    },
    {
      "query_id": "q_5136",
      "query_text": "Which \"Blackzilians\" fighter is currently competing in the Middleweight division of Ultimate Fighting Championship?",
      "dataset_name": "hotpotqa",
      "dataset_type": "HYBRID",
      "retrieved_doc_ids": [
        "doc_9eacd8ef3f75",
        "doc_779c28df935e",
        "doc_ee49745c596a",
        "doc_a7e13a39f5b3",
        "doc_3c477ba66154",
        "doc_9dc6f071bf77",
        "doc_af5deab52e58",
        "doc_d6e4d57c81d0",
        "doc_9ca9a6128e46",
        "doc_b6d496ab23c2",
        "doc_6daaec4f8c20",
        "doc_ef7e887cd08e",
        "doc_d929f815af19",
        "doc_7c5d91c79a7b",
        "doc_8b39bd8155e8",
        "doc_37e162b1a2ba",
        "doc_9c37c1b457ca",
        "doc_52c134cc0590",
        "doc_0ae0455499da",
        "doc_d6f528823bb6"
      ],
      "hit_at_k": {
        "1": 1.0,
        "3": 1.0,
        "5": 1.0,
        "10": 1.0,
        "20": 1.0
      },
      "recall_at_k": {
        "1": 0.5,
        "3": 1.0,
        "5": 1.0,
        "10": 1.0,
        "20": 1.0
      },
      "ndcg_at_k": {
        "1": 1.0,
        "3": 1.0,
        "5": 1.0,
        "10": 1.0,
        "20": 1.0
      },
      "mrr": 1.0,
      "generated_response": "Vitor Belfort",
      "expected_response": "Vitor Belfort",
      "primary_metric_type": "f1_score",
      "primary_metric_value": 1.0,
      "secondary_metrics": {
        "exact_match": 1.0,
        "faithfulness": 1.0
      },
      "status": "completed",
      "generation_doc_ids": [
        "doc_779c28df935e",
        "doc_9eacd8ef3f75",
        "doc_ee49745c596a",
        "doc_b6d496ab23c2",
        "doc_9dc6f071bf77"
      ],
      "generation_recall": 1.0,
      "generation_hit": 1.0,
      "pre_rerank_candidate_ids": [
        "doc_9eacd8ef3f75",
        "doc_779c28df935e",
        "doc_ee49745c596a",
        "doc_a7e13a39f5b3",
        "doc_3c477ba66154",
        "doc_9dc6f071bf77",
        "doc_af5deab52e58",
        "doc_d6e4d57c81d0",
        "doc_9ca9a6128e46",
        "doc_b6d496ab23c2",
        "doc_6daaec4f8c20",
        "doc_ef7e887cd08e",
        "doc_d929f815af19",
        "doc_7c5d91c79a7b",
        "doc_8b39bd8155e8",
        "doc_37e162b1a2ba",
        "doc_9c37c1b457ca",
        "doc_52c134cc0590",
        "doc_0ae0455499da",
        "doc_d6f528823bb6"
      ],
      "metadata": {
        "question_type": "bridge",
        "level": "hard",
        "reranked": true
      }
    },
    {
      "query_id": "q_4151",
      "query_text": "Were was the Mexican state after which there is Villa Unión, Sinaloa located? ",
      "dataset_name": "hotpotqa",
      "dataset_type": "HYBRID",
      "retrieved_doc_ids": [
        "doc_ef660eb73d13",
        "doc_fadfd6a4ebf6",
        "doc_3c1214e16c85",
        "doc_1990e26b9f73",
        "doc_c0c8c3bc6b4e",
        "doc_211f963507d2",
        "doc_7deb27efc3ce",
        "doc_7c5d91c79a7b",
        "doc_139b160626df",
        "doc_86e0883be37b",
        "doc_a7e13a39f5b3",
        "doc_f1f7fc470259",
        "doc_55e3040f0f86",
        "doc_afb77097a95a",
        "doc_65d035cca47c",
        "doc_7e4f47d4508c",
        "doc_00a04413b36b",
        "doc_b4f7c87b8184",
        "doc_5fdf6c4bf8d4",
        "doc_d6e4d57c81d0"
      ],
      "hit_at_k": {
        "1": 0.0,
        "3": 1.0,
        "5": 1.0,
        "10": 1.0,
        "20": 1.0
      },
      "recall_at_k": {
        "1": 0.0,
        "3": 1.0,
        "5": 1.0,
        "10": 1.0,
        "20": 1.0
      },
      "ndcg_at_k": {
        "1": 0.0,
        "3": 0.6934264036172708,
        "5": 0.6934264036172708,
        "10": 0.6934264036172708,
        "20": 0.6934264036172708
      },
      "mrr": 0.5,
      "generated_response": "Sinaloa",
      "expected_response": "tip of the Baja California",
      "primary_metric_type": "f1_score",
      "primary_metric_value": 0.0,
      "secondary_metrics": {
        "exact_match": 0.0,
        "faithfulness": 1.0
      },
      "status": "completed",
      "generation_doc_ids": [
        "doc_3c1214e16c85",
        "doc_fadfd6a4ebf6",
        "doc_211f963507d2",
        "doc_5fdf6c4bf8d4",
        "doc_7c5d91c79a7b"
      ],
      "generation_recall": 1.0,
      "generation_hit": 1.0,
      "pre_rerank_candidate_ids": [
        "doc_ef660eb73d13",
        "doc_fadfd6a4ebf6",
        "doc_3c1214e16c85",
        "doc_1990e26b9f73",
        "doc_c0c8c3bc6b4e",
        "doc_211f963507d2",
        "doc_7deb27efc3ce",
        "doc_7c5d91c79a7b",
        "doc_139b160626df",
        "doc_86e0883be37b",
        "doc_a7e13a39f5b3",
        "doc_f1f7fc470259",
        "doc_55e3040f0f86",
        "doc_afb77097a95a",
        "doc_65d035cca47c",
        "doc_7e4f47d4508c",
        "doc_00a04413b36b",
        "doc_b4f7c87b8184",
        "doc_5fdf6c4bf8d4",
        "doc_d6e4d57c81d0"
      ],
      "metadata": {
        "question_type": "bridge",
        "level": "hard",
        "reranked": true
      }
    },
    {
      "query_id": "q_4456",
      "query_text": "What language, traditionally written with the ancient Libyco-Berber script, is closely related to the Tumzabt and Teggargrent languages?",
      "dataset_name": "hotpotqa",
      "dataset_type": "HYBRID",
      "retrieved_doc_ids": [
        "doc_ebc4f5884bdc",
        "doc_84b01e2fdcbc",
        "doc_9ef67372a3dd",
        "doc_5fdf6c4bf8d4",
        "doc_d6e4d57c81d0",
        "doc_8b758fdc9ceb",
        "doc_6f0f1f67cd06",
        "doc_8b75cb852844",
        "doc_87d5e2fe56d5",
        "doc_0995a2f3e44e",
        "doc_3a73b3cfa32e",
        "doc_071a063f5e55",
        "doc_7c5d91c79a7b",
        "doc_4c3a0c2fd6fb",
        "doc_129e702e719c",
        "doc_00a04413b36b",
        "doc_76ec15f72159",
        "doc_6697a1536fde",
        "doc_afb77097a95a",
        "doc_65d035cca47c"
      ],
      "hit_at_k": {
        "1": 1.0,
        "3": 1.0,
        "5": 1.0,
        "10": 1.0,
        "20": 1.0
      },
      "recall_at_k": {
        "1": 0.5,
        "3": 1.0,
        "5": 1.0,
        "10": 1.0,
        "20": 1.0
      },
      "ndcg_at_k": {
        "1": 1.0,
        "3": 1.0,
        "5": 1.0,
        "10": 1.0,
        "20": 1.0
      },
      "mrr": 1.0,
      "generated_response": "Tugurt",
      "expected_response": "The Tugurt language",
      "primary_metric_type": "f1_score",
      "primary_metric_value": 0.5,
      "secondary_metrics": {
        "exact_match": 0.0,
        "faithfulness": 1.0
      },
      "status": "completed",
      "generation_doc_ids": [
        "doc_ebc4f5884bdc",
        "doc_84b01e2fdcbc",
        "doc_afb77097a95a",
        "doc_129e702e719c",
        "doc_9ef67372a3dd"
      ],
      "generation_recall": 1.0,
      "generation_hit": 1.0,
      "pre_rerank_candidate_ids": [
        "doc_ebc4f5884bdc",
        "doc_84b01e2fdcbc",
        "doc_9ef67372a3dd",
        "doc_5fdf6c4bf8d4",
        "doc_d6e4d57c81d0",
        "doc_8b758fdc9ceb",
        "doc_6f0f1f67cd06",
        "doc_8b75cb852844",
        "doc_87d5e2fe56d5",
        "doc_0995a2f3e44e",
        "doc_3a73b3cfa32e",
        "doc_071a063f5e55",
        "doc_7c5d91c79a7b",
        "doc_4c3a0c2fd6fb",
        "doc_129e702e719c",
        "doc_00a04413b36b",
        "doc_76ec15f72159",
        "doc_6697a1536fde",
        "doc_afb77097a95a",
        "doc_65d035cca47c"
      ],
      "metadata": {
        "question_type": "bridge",
        "level": "hard",
        "reranked": true
      }
    },
    {
      "query_id": "q_6054",
      "query_text": "Who is the fictional head of a British Secret Service division and for which a one-time missionary was the inspiration for?",
      "dataset_name": "hotpotqa",
      "dataset_type": "HYBRID",
      "retrieved_doc_ids": [
        "doc_44076348833d",
        "doc_31d6ca949522",
        "doc_8fa98ed8a4de",
        "doc_efeebe340ffc",
        "doc_5169828aec2d",
        "doc_5986bde91db9",
        "doc_81412511d564",
        "doc_6b2f2e5fb49e",
        "doc_77bc3fd24090",
        "doc_5fdf6c4bf8d4",
        "doc_fbea6547c451",
        "doc_00a04413b36b",
        "doc_afb77097a95a",
        "doc_3c00efdbc637",
        "doc_d6f528823bb6",
        "doc_f70086c00f28",
        "doc_7c5d91c79a7b",
        "doc_d6e4d57c81d0",
        "doc_7979fddcd667",
        "doc_a82ced61114c"
      ],
      "hit_at_k": {
        "1": 0.0,
        "3": 1.0,
        "5": 1.0,
        "10": 1.0,
        "20": 1.0
      },
      "recall_at_k": {
        "1": 0.0,
        "3": 0.5,
        "5": 1.0,
        "10": 1.0,
        "20": 1.0
      },
      "ndcg_at_k": {
        "1": 0.0,
        "3": 0.38685280723454163,
        "5": 0.6240505200038379,
        "10": 0.6240505200038379,
        "20": 0.6240505200038379
      },
      "mrr": 0.5,
      "generated_response": "Q",
      "expected_response": "Q",
      "primary_metric_type": "f1_score",
      "primary_metric_value": 1.0,
      "secondary_metrics": {
        "exact_match": 1.0,
        "faithfulness": 1.0
      },
      "status": "completed",
      "generation_doc_ids": [
        "doc_5169828aec2d",
        "doc_31d6ca949522",
        "doc_efeebe340ffc",
        "doc_6b2f2e5fb49e",
        "doc_5986bde91db9"
      ],
      "generation_recall": 1.0,
      "generation_hit": 1.0,
      "pre_rerank_candidate_ids": [
        "doc_44076348833d",
        "doc_31d6ca949522",
        "doc_8fa98ed8a4de",
        "doc_efeebe340ffc",
        "doc_5169828aec2d",
        "doc_5986bde91db9",
        "doc_81412511d564",
        "doc_6b2f2e5fb49e",
        "doc_77bc3fd24090",
        "doc_5fdf6c4bf8d4",
        "doc_fbea6547c451",
        "doc_00a04413b36b",
        "doc_afb77097a95a",
        "doc_3c00efdbc637",
        "doc_d6f528823bb6",
        "doc_f70086c00f28",
        "doc_7c5d91c79a7b",
        "doc_d6e4d57c81d0",
        "doc_7979fddcd667",
        "doc_a82ced61114c"
      ],
      "metadata": {
        "question_type": "bridge",
        "level": "hard",
        "reranked": true
      }
    },
    {
      "query_id": "q_7110",
      "query_text": "Phillip Pullman's book set in a parallel universe featuring a character named Lyra Belacqua was put into audio in what year?",
      "dataset_name": "hotpotqa",
      "dataset_type": "HYBRID",
      "retrieved_doc_ids": [
        "doc_e1f1d6e98de7",
        "doc_cb104c80e257",
        "doc_d6e4d57c81d0",
        "doc_d929f815af19",
        "doc_1c2c1975db80",
        "doc_071a063f5e55",
        "doc_c5536276d3f3",
        "doc_6ec65ee7cb7e",
        "doc_7ec40fdf159a",
        "doc_8b758fdc9ceb",
        "doc_ef8fb9f55437",
        "doc_1fce01119cca",
        "doc_b40e7e370e3a",
        "doc_6a86ec45ff1c",
        "doc_65d035cca47c",
        "doc_baae7588c8fb",
        "doc_a82ced61114c",
        "doc_65facdd0e2c1",
        "doc_5986bde91db9",
        "doc_afb77097a95a"
      ],
      "hit_at_k": {
        "1": 0.0,
        "3": 1.0,
        "5": 1.0,
        "10": 1.0,
        "20": 1.0
      },
      "recall_at_k": {
        "1": 0.0,
        "3": 0.5,
        "5": 0.5,
        "10": 0.5,
        "20": 1.0
      },
      "ndcg_at_k": {
        "1": 0.0,
        "3": 0.38685280723454163,
        "5": 0.38685280723454163,
        "10": 0.38685280723454163,
        "20": 0.526448181099292
      },
      "mrr": 0.5,
      "generated_response": "2002",
      "expected_response": "2002",
      "primary_metric_type": "f1_score",
      "primary_metric_value": 1.0,
      "secondary_metrics": {
        "exact_match": 1.0,
        "faithfulness": 1.0
      },
      "status": "completed",
      "generation_doc_ids": [
        "doc_cb104c80e257",
        "doc_afb77097a95a",
        "doc_baae7588c8fb",
        "doc_a82ced61114c",
        "doc_071a063f5e55"
      ],
      "generation_recall": 1.0,
      "generation_hit": 1.0,
      "pre_rerank_candidate_ids": [
        "doc_e1f1d6e98de7",
        "doc_cb104c80e257",
        "doc_d6e4d57c81d0",
        "doc_d929f815af19",
        "doc_1c2c1975db80",
        "doc_071a063f5e55",
        "doc_c5536276d3f3",
        "doc_6ec65ee7cb7e",
        "doc_7ec40fdf159a",
        "doc_8b758fdc9ceb",
        "doc_ef8fb9f55437",
        "doc_1fce01119cca",
        "doc_b40e7e370e3a",
        "doc_6a86ec45ff1c",
        "doc_65d035cca47c",
        "doc_baae7588c8fb",
        "doc_a82ced61114c",
        "doc_65facdd0e2c1",
        "doc_5986bde91db9",
        "doc_afb77097a95a"
      ],
      "metadata": {
        "question_type": "bridge",
        "level": "hard",
        "reranked": true
      }
    },
    {
      "query_id": "q_4166",
      "query_text": "Who directed the second film in a British series of action comedy film parodying the James Bond secret agent genre with comedy similar to Rowan Atkinson's Mr. Bean character?",
      "dataset_name": "hotpotqa",
      "dataset_type": "HYBRID",
      "retrieved_doc_ids": [
        "doc_2bbf0bf094d7",
        "doc_decab0c612f1",
        "doc_fea83f45526b",
        "doc_6b2f2e5fb49e",
        "doc_efeebe340ffc",
        "doc_d929f815af19",
        "doc_5169828aec2d",
        "doc_cb551c86450e",
        "doc_5986bde91db9",
        "doc_daf00a922da9",
        "doc_81412511d564",
        "doc_031d2763fccc",
        "doc_0995a2f3e44e",
        "doc_d6e4d57c81d0",
        "doc_af5deab52e58",
        "doc_e1f1d6e98de7",
        "doc_77bc3fd24090",
        "doc_67ee46d848f9",
        "doc_a5544235543c",
        "doc_31d6ca949522"
      ],
      "hit_at_k": {
        "1": 0.0,
        "3": 0.0,
        "5": 1.0,
        "10": 1.0,
        "20": 1.0
      },
      "recall_at_k": {
        "1": 0.0,
        "3": 0.0,
        "5": 1.0,
        "10": 1.0,
        "20": 1.0
      },
      "ndcg_at_k": {
        "1": 0.0,
        "3": 0.0,
        "5": 0.5012658353418871,
        "10": 0.5012658353418871,
        "20": 0.5012658353418871
      },
      "mrr": 0.25,
      "generated_response": "Oliver Parker",
      "expected_response": "Oliver Parker",
      "primary_metric_type": "f1_score",
      "primary_metric_value": 1.0,
      "secondary_metrics": {
        "exact_match": 1.0,
        "faithfulness": 1.0
      },
      "status": "completed",
      "generation_doc_ids": [
        "doc_6b2f2e5fb49e",
        "doc_efeebe340ffc",
        "doc_a5544235543c",
        "doc_31d6ca949522",
        "doc_daf00a922da9"
      ],
      "generation_recall": 1.0,
      "generation_hit": 1.0,
      "pre_rerank_candidate_ids": [
        "doc_2bbf0bf094d7",
        "doc_decab0c612f1",
        "doc_fea83f45526b",
        "doc_6b2f2e5fb49e",
        "doc_efeebe340ffc",
        "doc_d929f815af19",
        "doc_5169828aec2d",
        "doc_cb551c86450e",
        "doc_5986bde91db9",
        "doc_daf00a922da9",
        "doc_81412511d564",
        "doc_031d2763fccc",
        "doc_0995a2f3e44e",
        "doc_d6e4d57c81d0",
        "doc_af5deab52e58",
        "doc_e1f1d6e98de7",
        "doc_77bc3fd24090",
        "doc_67ee46d848f9",
        "doc_a5544235543c",
        "doc_31d6ca949522"
      ],
      "metadata": {
        "question_type": "bridge",
        "level": "hard",
        "reranked": true
      }
    },
    {
      "query_id": "q_1564",
      "query_text": "George Gershwin is an American Composer and Judith Weir is a composer from which country?",
      "dataset_name": "hotpotqa",
      "dataset_type": "HYBRID",
      "retrieved_doc_ids": [
        "doc_a468aae57b0c",
        "doc_30044ac84f30",
        "doc_7c5d91c79a7b",
        "doc_0addee5fd296",
        "doc_a84ce549483b",
        "doc_6af21c618760",
        "doc_0ba117f98849",
        "doc_6520fa938322",
        "doc_52c134cc0590",
        "doc_8c16ba69ce77",
        "doc_129e702e719c",
        "doc_44076348833d",
        "doc_c695d5d388a9",
        "doc_2e4bd88bbd50",
        "doc_8b758fdc9ceb",
        "doc_32bbc03c3840",
        "doc_d6e4d57c81d0",
        "doc_ef7e887cd08e",
        "doc_b6eeb54f8777",
        "doc_baae7588c8fb"
      ],
      "hit_at_k": {
        "1": 0.0,
        "3": 1.0,
        "5": 1.0,
        "10": 1.0,
        "20": 1.0
      },
      "recall_at_k": {
        "1": 0.0,
        "3": 0.5,
        "5": 1.0,
        "10": 1.0,
        "20": 1.0
      },
      "ndcg_at_k": {
        "1": 0.0,
        "3": 0.38685280723454163,
        "5": 0.6240505200038379,
        "10": 0.6240505200038379,
        "20": 0.6240505200038379
      },
      "mrr": 0.5,
      "generated_response": "British",
      "expected_response": "a British composer",
      "primary_metric_type": "accuracy",
      "primary_metric_value": 0.0,
      "secondary_metrics": {
        "f1_score": 0.5,
        "exact_match": 0.0,
        "faithfulness": 1.0
      },
      "status": "completed",
      "generation_doc_ids": [
        "doc_a84ce549483b",
        "doc_30044ac84f30",
        "doc_0addee5fd296",
        "doc_0ba117f98849",
        "doc_129e702e719c"
      ],
      "generation_recall": 1.0,
      "generation_hit": 1.0,
      "pre_rerank_candidate_ids": [
        "doc_a468aae57b0c",
        "doc_30044ac84f30",
        "doc_7c5d91c79a7b",
        "doc_0addee5fd296",
        "doc_a84ce549483b",
        "doc_6af21c618760",
        "doc_0ba117f98849",
        "doc_6520fa938322",
        "doc_52c134cc0590",
        "doc_8c16ba69ce77",
        "doc_129e702e719c",
        "doc_44076348833d",
        "doc_c695d5d388a9",
        "doc_2e4bd88bbd50",
        "doc_8b758fdc9ceb",
        "doc_32bbc03c3840",
        "doc_d6e4d57c81d0",
        "doc_ef7e887cd08e",
        "doc_b6eeb54f8777",
        "doc_baae7588c8fb"
      ],
      "metadata": {
        "question_type": "comparison",
        "level": "hard",
        "reranked": true
      }
    },
    {
      "query_id": "q_6694",
      "query_text": "What Was the name of Juan Manuel Márquez's  WBO champion holding younger brother?",
      "dataset_name": "hotpotqa",
      "dataset_type": "HYBRID",
      "retrieved_doc_ids": [
        "doc_d4209183df53",
        "doc_b6d496ab23c2",
        "doc_fcea7b45da83",
        "doc_f2bb89feac90",
        "doc_923d043d3d23",
        "doc_554029cc0bfd",
        "doc_8b758fdc9ceb",
        "doc_afb77097a95a",
        "doc_86e0883be37b",
        "doc_8b75cb852844",
        "doc_9ca9a6128e46",
        "doc_9dc6f071bf77",
        "doc_ee49745c596a",
        "doc_7c5d91c79a7b",
        "doc_15ddd6283333",
        "doc_f5795fa1d361",
        "doc_d6e4d57c81d0",
        "doc_bbb90cde213b",
        "doc_211f963507d2",
        "doc_a55ca63bc0ad"
      ],
      "hit_at_k": {
        "1": 1.0,
        "3": 1.0,
        "5": 1.0,
        "10": 1.0,
        "20": 1.0
      },
      "recall_at_k": {
        "1": 0.5,
        "3": 1.0,
        "5": 1.0,
        "10": 1.0,
        "20": 1.0
      },
      "ndcg_at_k": {
        "1": 1.0,
        "3": 1.0,
        "5": 1.0,
        "10": 1.0,
        "20": 1.0
      },
      "mrr": 1.0,
      "generated_response": "Rafael Márquez",
      "expected_response": "Rafael Márquez",
      "primary_metric_type": "f1_score",
      "primary_metric_value": 1.0,
      "secondary_metrics": {
        "exact_match": 1.0,
        "faithfulness": 1.0
      },
      "status": "completed",
      "generation_doc_ids": [
        "doc_d4209183df53",
        "doc_b6d496ab23c2",
        "doc_9dc6f071bf77",
        "doc_ee49745c596a",
        "doc_bbb90cde213b"
      ],
      "generation_recall": 1.0,
      "generation_hit": 1.0,
      "pre_rerank_candidate_ids": [
        "doc_d4209183df53",
        "doc_b6d496ab23c2",
        "doc_fcea7b45da83",
        "doc_f2bb89feac90",
        "doc_923d043d3d23",
        "doc_554029cc0bfd",
        "doc_8b758fdc9ceb",
        "doc_afb77097a95a",
        "doc_86e0883be37b",
        "doc_8b75cb852844",
        "doc_9ca9a6128e46",
        "doc_9dc6f071bf77",
        "doc_ee49745c596a",
        "doc_7c5d91c79a7b",
        "doc_15ddd6283333",
        "doc_f5795fa1d361",
        "doc_d6e4d57c81d0",
        "doc_bbb90cde213b",
        "doc_211f963507d2",
        "doc_a55ca63bc0ad"
      ],
      "metadata": {
        "question_type": "bridge",
        "level": "hard",
        "reranked": true
      }
    },
    {
      "query_id": "q_3802",
      "query_text": "The Running Man Brothers is a South Korean pop duo. Kim Jong-kook is one member and he is from what country?",
      "dataset_name": "hotpotqa",
      "dataset_type": "HYBRID",
      "retrieved_doc_ids": [
        "doc_6a161bb8067e",
        "doc_d966845ed38a",
        "doc_160e9813b328",
        "doc_554029cc0bfd",
        "doc_bbc866fee46a",
        "doc_129e702e719c",
        "doc_894cc382144a",
        "doc_97efeab02928",
        "doc_b1532a949a53",
        "doc_9ca9a6128e46",
        "doc_0d5a96d6bb90",
        "doc_c37a79b46976",
        "doc_501ebdc6d35b",
        "doc_b6eeb54f8777",
        "doc_00a04413b36b",
        "doc_139b160626df",
        "doc_0d48addd4a1e",
        "doc_a55ca63bc0ad",
        "doc_87291ed630df",
        "doc_bfbf7c24d39e"
      ],
      "hit_at_k": {
        "1": 0.0,
        "3": 1.0,
        "5": 1.0,
        "10": 1.0,
        "20": 1.0
      },
      "recall_at_k": {
        "1": 0.0,
        "3": 0.5,
        "5": 1.0,
        "10": 1.0,
        "20": 1.0
      },
      "ndcg_at_k": {
        "1": 0.0,
        "3": 0.38685280723454163,
        "5": 0.6509209298071326,
        "10": 0.6509209298071326,
        "20": 0.6509209298071326
      },
      "mrr": 0.5,
      "generated_response": "South Korea",
      "expected_response": "South Korea",
      "primary_metric_type": "f1_score",
      "primary_metric_value": 1.0,
      "secondary_metrics": {
        "exact_match": 1.0,
        "faithfulness": 1.0
      },
      "status": "completed",
      "generation_doc_ids": [
        "doc_554029cc0bfd",
        "doc_d966845ed38a",
        "doc_160e9813b328",
        "doc_bfbf7c24d39e",
        "doc_97efeab02928"
      ],
      "generation_recall": 1.0,
      "generation_hit": 1.0,
      "pre_rerank_candidate_ids": [
        "doc_6a161bb8067e",
        "doc_d966845ed38a",
        "doc_160e9813b328",
        "doc_554029cc0bfd",
        "doc_bbc866fee46a",
        "doc_129e702e719c",
        "doc_894cc382144a",
        "doc_97efeab02928",
        "doc_b1532a949a53",
        "doc_9ca9a6128e46",
        "doc_0d5a96d6bb90",
        "doc_c37a79b46976",
        "doc_501ebdc6d35b",
        "doc_b6eeb54f8777",
        "doc_00a04413b36b",
        "doc_139b160626df",
        "doc_0d48addd4a1e",
        "doc_a55ca63bc0ad",
        "doc_87291ed630df",
        "doc_bfbf7c24d39e"
      ],
      "metadata": {
        "question_type": "bridge",
        "level": "hard",
        "reranked": true
      }
    },
    {
      "query_id": "q_7043",
      "query_text": "Ruddles Brewery is owned by a pub retailer and brewer based in what city?",
      "dataset_name": "hotpotqa",
      "dataset_type": "HYBRID",
      "retrieved_doc_ids": [
        "doc_03b3b30c344f",
        "doc_f47338c9996b",
        "doc_b9013f48c9c2",
        "doc_44076348833d",
        "doc_fac9396daef5",
        "doc_7c5d91c79a7b",
        "doc_a55ca63bc0ad",
        "doc_fcf4355e70fe",
        "doc_65d035cca47c",
        "doc_b4f7c87b8184",
        "doc_5c4e4acc8dff",
        "doc_c369ffe1233b",
        "doc_3001b694602a",
        "doc_49b5791d3dab",
        "doc_a82ced61114c",
        "doc_6520655af758",
        "doc_92bce083c96e",
        "doc_5c6fc68f377a",
        "doc_f5795fa1d361",
        "doc_baae7588c8fb"
      ],
      "hit_at_k": {
        "1": 1.0,
        "3": 1.0,
        "5": 1.0,
        "10": 1.0,
        "20": 1.0
      },
      "recall_at_k": {
        "1": 0.5,
        "3": 1.0,
        "5": 1.0,
        "10": 1.0,
        "20": 1.0
      },
      "ndcg_at_k": {
        "1": 1.0,
        "3": 1.0,
        "5": 1.0,
        "10": 1.0,
        "20": 1.0
      },
      "mrr": 1.0,
      "generated_response": "Bury St Edmunds",
      "expected_response": "Bury St Edmunds",
      "primary_metric_type": "f1_score",
      "primary_metric_value": 1.0,
      "secondary_metrics": {
        "exact_match": 1.0,
        "faithfulness": 1.0
      },
      "status": "completed",
      "generation_doc_ids": [
        "doc_f47338c9996b",
        "doc_03b3b30c344f",
        "doc_baae7588c8fb",
        "doc_fcf4355e70fe",
        "doc_5c6fc68f377a"
      ],
      "generation_recall": 1.0,
      "generation_hit": 1.0,
      "pre_rerank_candidate_ids": [
        "doc_03b3b30c344f",
        "doc_f47338c9996b",
        "doc_b9013f48c9c2",
        "doc_44076348833d",
        "doc_fac9396daef5",
        "doc_7c5d91c79a7b",
        "doc_a55ca63bc0ad",
        "doc_fcf4355e70fe",
        "doc_65d035cca47c",
        "doc_b4f7c87b8184",
        "doc_5c4e4acc8dff",
        "doc_c369ffe1233b",
        "doc_3001b694602a",
        "doc_49b5791d3dab",
        "doc_a82ced61114c",
        "doc_6520655af758",
        "doc_92bce083c96e",
        "doc_5c6fc68f377a",
        "doc_f5795fa1d361",
        "doc_baae7588c8fb"
      ],
      "metadata": {
        "question_type": "bridge",
        "level": "hard",
        "reranked": true
      }
    },
    {
      "query_id": "q_4109",
      "query_text": "The creator of the Lisa Simpson character was born in what year?",
      "dataset_name": "hotpotqa",
      "dataset_type": "HYBRID",
      "retrieved_doc_ids": [
        "doc_6e493e9d454a",
        "doc_7ec40fdf159a",
        "doc_f2bb89feac90",
        "doc_a84ce549483b",
        "doc_a1825ef4f106",
        "doc_baae7588c8fb",
        "doc_4dd1d7bee06f",
        "doc_8bff5d43c2cd",
        "doc_67ee46d848f9",
        "doc_86e0883be37b",
        "doc_afb77097a95a",
        "doc_52c134cc0590",
        "doc_3d07173b6fb7",
        "doc_a82ced61114c",
        "doc_15ddd6283333",
        "doc_d6e4d57c81d0",
        "doc_af67a9dc447c",
        "doc_81412511d564",
        "doc_7c5d91c79a7b",
        "doc_5986bde91db9"
      ],
      "hit_at_k": {
        "1": 1.0,
        "3": 1.0,
        "5": 1.0,
        "10": 1.0,
        "20": 1.0
      },
      "recall_at_k": {
        "1": 0.5,
        "3": 1.0,
        "5": 1.0,
        "10": 1.0,
        "20": 1.0
      },
      "ndcg_at_k": {
        "1": 1.0,
        "3": 1.0,
        "5": 1.0,
        "10": 1.0,
        "20": 1.0
      },
      "mrr": 1.0,
      "generated_response": "1954",
      "expected_response": "1954",
      "primary_metric_type": "f1_score",
      "primary_metric_value": 1.0,
      "secondary_metrics": {
        "exact_match": 1.0,
        "faithfulness": 1.0
      },
      "status": "completed",
      "generation_doc_ids": [
        "doc_7ec40fdf159a",
        "doc_6e493e9d454a",
        "doc_8bff5d43c2cd",
        "doc_15ddd6283333",
        "doc_a1825ef4f106"
      ],
      "generation_recall": 1.0,
      "generation_hit": 1.0,
      "pre_rerank_candidate_ids": [
        "doc_6e493e9d454a",
        "doc_7ec40fdf159a",
        "doc_f2bb89feac90",
        "doc_a84ce549483b",
        "doc_a1825ef4f106",
        "doc_baae7588c8fb",
        "doc_4dd1d7bee06f",
        "doc_8bff5d43c2cd",
        "doc_67ee46d848f9",
        "doc_86e0883be37b",
        "doc_afb77097a95a",
        "doc_52c134cc0590",
        "doc_3d07173b6fb7",
        "doc_a82ced61114c",
        "doc_15ddd6283333",
        "doc_d6e4d57c81d0",
        "doc_af67a9dc447c",
        "doc_81412511d564",
        "doc_7c5d91c79a7b",
        "doc_5986bde91db9"
      ],
      "metadata": {
        "question_type": "bridge",
        "level": "hard",
        "reranked": true
      }
    },
    {
      "query_id": "q_4368",
      "query_text": "Where is the international airport which Eagle Aviation wet lease operations were based in located ",
      "dataset_name": "hotpotqa",
      "dataset_type": "HYBRID",
      "retrieved_doc_ids": [
        "doc_616555aa7dc6",
        "doc_1da179de0fe2",
        "doc_411f37fd2096",
        "doc_3b5f58b4f858",
        "doc_153c9da382d7",
        "doc_6518bffa8a2e",
        "doc_a7ae162d3f84",
        "doc_3952dbef23ec",
        "doc_86f4562c2b57",
        "doc_6daaec4f8c20",
        "doc_3001b694602a",
        "doc_766ef1db3e97",
        "doc_2bbf0bf094d7",
        "doc_65d035cca47c",
        "doc_d6e4d57c81d0",
        "doc_0995a2f3e44e",
        "doc_3c00efdbc637",
        "doc_86e0883be37b",
        "doc_7e4f47d4508c",
        "doc_071a063f5e55"
      ],
      "hit_at_k": {
        "1": 0.0,
        "3": 0.0,
        "5": 0.0,
        "10": 1.0,
        "20": 1.0
      },
      "recall_at_k": {
        "1": 0.0,
        "3": 0.0,
        "5": 0.0,
        "10": 0.5,
        "20": 1.0
      },
      "ndcg_at_k": {
        "1": 0.0,
        "3": 0.0,
        "5": 0.0,
        "10": 0.20438239758848611,
        "20": 0.3754154816562042
      },
      "mrr": 0.14285714285714285,
      "generated_response": "Paris, France",
      "expected_response": "France.",
      "primary_metric_type": "f1_score",
      "primary_metric_value": 0.6667,
      "secondary_metrics": {
        "exact_match": 0.0,
        "faithfulness": 1.0
      },
      "status": "completed",
      "generation_doc_ids": [
        "doc_3001b694602a",
        "doc_411f37fd2096",
        "doc_616555aa7dc6",
        "doc_a7ae162d3f84",
        "doc_6518bffa8a2e"
      ],
      "generation_recall": 1.0,
      "generation_hit": 1.0,
      "pre_rerank_candidate_ids": [
        "doc_616555aa7dc6",
        "doc_1da179de0fe2",
        "doc_411f37fd2096",
        "doc_3b5f58b4f858",
        "doc_153c9da382d7",
        "doc_6518bffa8a2e",
        "doc_a7ae162d3f84",
        "doc_3952dbef23ec",
        "doc_86f4562c2b57",
        "doc_6daaec4f8c20",
        "doc_3001b694602a",
        "doc_766ef1db3e97",
        "doc_2bbf0bf094d7",
        "doc_65d035cca47c",
        "doc_d6e4d57c81d0",
        "doc_0995a2f3e44e",
        "doc_3c00efdbc637",
        "doc_86e0883be37b",
        "doc_7e4f47d4508c",
        "doc_071a063f5e55"
      ],
      "metadata": {
        "question_type": "bridge",
        "level": "hard",
        "reranked": true
      }
    }
  ]
}